{"path":".obsidian/plugins/text-extractor/cache/sk/content-attachments-skeemo-statblock-png-114e201a531302d58a26ba3f1d5e50ae.json","text":"Spellcasting. Skeemo is a 9th-level spellcaster. His SKEEMO WEIRDBOTTLE ke G, 3 : spellcasting ability is Intelligence (spell save DC 14, +6 Small Humanoid (Gnome), Neutral Evil to hit with spell attacks). He has the following wizard spells prepared: Armor Class 12 (15 with mage armor) Cantrips (at will): fire bolt, light, mage hand, Hit Points 72 (16d6 + 16) prestidigitation Speed 25 fi. 1st level (4 slots): detect magic, mage armor, magic ——_—_—___eE missile, shield B DEX cON (s i el 2nd level (3 slots): misty step, suggestion 9 (1) 14 (+2) 12 1) 17 (#3) 12 (+1) 15 (+2) G - 3rd level (3 slots): counterspell, fireball, fly Saving Throws INT +6, WIS +4 4th level (3 slots): greater invisibility, ice storm il;llls Arcana +6, History +6, Perception +4, Performance Sehl SV D e R hcold Senses Darkvision 60 ft., Passive Perception 14 f Languages Abyssal, Common, Gnomish, Undercommon ACtIonS Ehalenzalciiz il Broficincy Boulsed Dagger. Melee or Ranged Weapon Attack: +5 to hit, reach g e L e Y R 5 ft. or range 20/60 ft., one target. Hit: 4 (1d4 + 2) piercing damage. Gnome Cunning. Skeemo has advantage on Intelligence, Wisdom, and Charisma saving throws against magic.","libVersion":"0.0.0","langs":"eng","hash":"","size":0}